{"cameraMode":{"drawMode":0,"name":"Shaded","section":"Shading Mode"},"sceneLighting":true,"audioPlay":false,"sceneViewState":{"m_AlwaysRefresh":false,"showFog":true,"showSkybox":true,"showFlares":true,"showImageEffects":true,"showParticleSystems":true,"showVisualEffectGraphs":true,"m_FxEnabled":true},"in2DMode":false,"pivot":{"x":4.202800750732422,"y":5.375342845916748,"z":4.560848236083984},"rotation":{"x":-0.0819670781493187,"y":-0.2910073399543762,"z":0.0250326506793499,"w":-0.9528746604919434},"size":62.534828186035159,"orthographic":false}